bbfreeze/__init__.py
bbfreeze/__main__.py
bbfreeze/bdist_bbfreeze.py
bbfreeze/codehack.py
bbfreeze/eggutil.py
bbfreeze/ensure_setuptools.py
bbfreeze/freezer.py
bbfreeze/getdeps.py
bbfreeze/load_console.py
bbfreeze/py.py
bbfreeze/recipes.py
bbfreeze/winexeutil.py
bbfreeze/modulegraph/__init__.py
bbfreeze/modulegraph/find_modules.py
bbfreeze/modulegraph/modulegraph.py
bbfreeze/modulegraph/util.py
refrigerant-1.1.11.dist-info/METADATA
refrigerant-1.1.11.dist-info/WHEEL
refrigerant-1.1.11.dist-info/entry_points.txt
refrigerant-1.1.11.dist-info/top_level.txt
refrigerant-1.1.11.dist-info/RECORD
