Metadata-Version: 2.1
Name: refrigerant
Version: 1.1.11
Summary: create standalone executables from python scripts
Home-page: https://pypi.python.org/pypi/refrigerant/
Maintainer: Ross J. Duff
Maintainer-email: rjdbcm@mail.umkc.edu
License: zlib/libpng license
Platform: Linux Windows
Classifier: Development Status :: 5 - Production/Stable
Classifier: License :: OSI Approved :: zlib/libpng License
Classifier: Intended Audience :: Developers
Classifier: Programming Language :: Python
Classifier: Programming Language :: Python :: 2
Classifier: Programming Language :: Python :: 2.4
Classifier: Programming Language :: Python :: 2.5
Classifier: Programming Language :: Python :: 2.6
Classifier: Programming Language :: Python :: 2.7
Classifier: Topic :: Software Development :: Build Tools
Classifier: Topic :: System :: Software Distribution
Requires-Dist: altgraph (==0.9)
Requires-Dist: refrigerant-loader (<1.2.0,>=1.1.0)
